clearlib/config.py
clearlib/lexicon/LexiconEntry.py
clearlib/lexicon/__init__.py
clearlib/lexicon/ubsdgnt.py
clearlib/load_license.py
clearlib/util/__init__.py
clearlib/util/listalign.py
clearlib-0.1.5.dist-info/LICENSE
clearlib-0.1.5.dist-info/METADATA
clearlib-0.1.5.dist-info/WHEEL
clearlib-0.1.5.dist-info/RECORD
