Metadata-Version: 2.1
Name: Clearlib
Version: 0.1.5
Summary: Internal common utilities for working with various data.
License: MIT
Author: Sean Boisen
Author-email: sean.boisen@biblica.com
Requires-Python: >=3.8,<4
Classifier: License :: OSI Approved :: MIT License
Classifier: Operating System :: OS Independent
Classifier: Programming Language :: Python :: 3
Classifier: Programming Language :: Python :: 3.8
Classifier: Programming Language :: Python :: 3.9
Classifier: Programming Language :: Python :: 3.10
Classifier: Programming Language :: Python :: 3.11
Classifier: Programming Language :: Python :: 3.12
Requires-Dist: biblelib (>=0.3.2,<0.4.0)
Requires-Dist: lxml (>=5.1.0,<6.0.0)
Requires-Dist: unicodecsv (>=0.14.1,<0.15.0)
